{
  "$schema": "https://schema.management.azure.com/schemas/2019-04-01/deploymentTemplate.json#",
  "contentVersion": "1.0.0.0",
  "metadata": {
    "_generator": {
      "name": "bicep",
      "version": "0.30.23.60470",
      "templateHash": "9323874743326251801"
    }
  },
  "variables": {
    "location": "[resourceGroup().location]",
    "osDiskSizeGB": 128,
    "agentCount": 1,
    "agentVMSize": "Standard_D2s_v3",
    "osTypeLinux": "Linux"
  },
  "resources": [
    {
      "type": "Microsoft.ContainerService/managedClusters",
      "apiVersion": "2024-02-01",
      "name": "ExistingCluster",
      "location": "[variables('location')]",
      "tags": {
        "displayname": "Existing AKS Cluster"
      },
      "identity": {
        "type": "SystemAssigned"
      },
      "properties": {
        "enableRBAC": true,
        "dnsPrefix": "devcluster",
        "agentPoolProfiles": [
          {
            "name": "syspool",
            "osDiskSizeGB": "[variables('osDiskSizeGB')]",
            "count": "[variables('agentCount')]",
            "vmSize": "[variables('agentVMSize')]",
            "osType": "[variables('osTypeLinux')]",
            "type": "VirtualMachineScaleSets",
            "mode": "System"
          }
        ]
      }
    }
  ]
}